setup.py
phoenix_ml8/Framework.py
phoenix_ml8/__init__.py
phoenix_ml8.egg-info/PKG-INFO
phoenix_ml8.egg-info/SOURCES.txt
phoenix_ml8.egg-info/dependency_links.txt
phoenix_ml8.egg-info/not-zip-safe
phoenix_ml8.egg-info/top_level.txt