Metadata-Version: 1.0
Name: phoenix-ml8
Version: 0.1
Summary: Machine Learning FrameWork
Home-page: UNKNOWN
Author: UNKNOWN
Author-email: UNKNOWN
License: UNKNOWN
Platform: UNKNOWN
